lincbrain/__init__.py
lincbrain/_version.py
lincbrain/conftest.py
lincbrain/consts.py
lincbrain/dandiapi.py
lincbrain/dandiarchive.py
lincbrain/dandiset.py
lincbrain/delete.py
lincbrain/download.py
lincbrain/due.py
lincbrain/exceptions.py
lincbrain/keyring.py
lincbrain/misctypes.py
lincbrain/move.py
lincbrain/organize.py
lincbrain/pynwb_utils.py
lincbrain/upload.py
lincbrain/utils.py
lincbrain/validate.py
lincbrain/validate_types.py
lincbrain/cli/__init__.py
lincbrain/cli/base.py
lincbrain/cli/cmd_delete.py
lincbrain/cli/cmd_digest.py
lincbrain/cli/cmd_download.py
lincbrain/cli/cmd_instances.py
lincbrain/cli/cmd_ls.py
lincbrain/cli/cmd_move.py
lincbrain/cli/cmd_organize.py
lincbrain/cli/cmd_service_scripts.py
lincbrain/cli/cmd_shell_completion.py
lincbrain/cli/cmd_upload.py
lincbrain/cli/cmd_validate.py
lincbrain/cli/command.py
lincbrain/cli/formatter.py
lincbrain/cli/tests/__init__.py
lincbrain/cli/tests/test_cmd_ls.py
lincbrain/cli/tests/test_cmd_validate.py
lincbrain/cli/tests/test_command.py
lincbrain/cli/tests/test_digest.py
lincbrain/cli/tests/test_download.py
lincbrain/cli/tests/test_formatter.py
lincbrain/cli/tests/test_instances.py
lincbrain/cli/tests/test_move.py
lincbrain/cli/tests/test_service_scripts.py
lincbrain/cli/tests/test_shell_completion.py
lincbrain/files/__init__.py
lincbrain/files/_private.py
lincbrain/files/bases.py
lincbrain/files/bids.py
lincbrain/files/zarr.py
lincbrain/metadata/__init__.py
lincbrain/metadata/core.py
lincbrain/metadata/nwb.py
lincbrain/metadata/util.py
lincbrain/support/__init__.py
lincbrain/support/digests.py
lincbrain/support/iterators.py
lincbrain/support/pyout.py
lincbrain/support/threaded_walk.py
lincbrain/support/tests/__init__.py
lincbrain/support/tests/test_digests.py
lincbrain/support/tests/test_iterators.py
lincbrain/tests/__init__.py
lincbrain/tests/fixtures.py
lincbrain/tests/skip.py
lincbrain/tests/test_dandiapi.py
lincbrain/tests/test_dandiarchive.py
lincbrain/tests/test_dandiset.py
lincbrain-1.0.4.dist-info/LICENSE
lincbrain-1.0.4.dist-info/METADATA
lincbrain-1.0.4.dist-info/WHEEL
lincbrain-1.0.4.dist-info/entry_points.txt
lincbrain-1.0.4.dist-info/top_level.txt
lincbrain-1.0.4.dist-info/RECORD
